LICENSE
MANIFEST.in
README.md
pyproject.toml
setup.py
easySpeech/__init__.py
easySpeech/flac-linux-x86
easySpeech/flac-linux-x86_64
easySpeech/flac-mac
easySpeech/flac-win32.exe
easySpeech/ml.py
easySpeech/recognize.py
easySpeech/record.py
easySpeech/speech.py
easySpeech.egg-info/PKG-INFO
easySpeech.egg-info/SOURCES.txt
easySpeech.egg-info/dependency_links.txt
easySpeech.egg-info/requires.txt
easySpeech.egg-info/top_level.txt