Metadata-Version: 2.1
Name: easySpeech
Version: 1.0.2
Summary: A python wrapper for google speech to text api
Home-page: https://github.com/SaptakBhoumik/easySpeech
Author: Saptak Bhoumik
Author-email: saptakbhoumik@gmail.com
License: MIT
Platform: UNKNOWN
Classifier: License :: OSI Approved :: MIT License
Classifier: Programming Language :: Python :: 3
License-File: LICENSE
